setup.py
distributions777/Binomialdistribution.py
distributions777/Gaussiandistribution.py
distributions777/Generaldistribution.py
distributions777/__init__.py
distributions777.egg-info/PKG-INFO
distributions777.egg-info/SOURCES.txt
distributions777.egg-info/dependency_links.txt
distributions777.egg-info/not-zip-safe
distributions777.egg-info/top_level.txt